butter_hopper/__init__.py
butter_hopper/config_helper.py
butter_hopper/executor.py
butter_hopper/headers.py
butter_hopper/main.py
butter_hopper/utils_base.py
butter_hopper/utils_exec.py
butter_hopper/utils_mount.py
tests/__init__.py
butter_hopper-0.2.0.dist-info/LICENSE.txt
butter_hopper-0.2.0.dist-info/METADATA
butter_hopper-0.2.0.dist-info/WHEEL
butter_hopper-0.2.0.dist-info/entry_points.txt
butter_hopper-0.2.0.dist-info/top_level.txt
butter_hopper-0.2.0.dist-info/RECORD
