Metadata-Version: 2.1
Name: butter-hopper
Version: 0.2.0
Summary: UNKNOWN
Home-page: https://github.com/cswl/butter-hopper
Author: Cswl Coldwind
Author-email: cswl1337@gmail.com
Maintainer: Cswl Coldwind
Maintainer-email: cswl1337@gmail.com
License: MIT
Platform: UNKNOWN
Classifier: Development Status :: 4 - Beta
Classifier: Intended Audience :: Developers
Classifier: License :: OSI Approved :: MIT License
Classifier: Natural Language :: English
Classifier: Operating System :: OS Independent
Classifier: Programming Language :: Python :: 3.6
Classifier: Programming Language :: Python :: Implementation :: CPython
Classifier: Programming Language :: Python :: Implementation :: PyPy
Requires-Dist: click
Requires-Dist: shell
Requires-Dist: munch
Requires-Dist: ruamel.yaml
